gtag/__init__.py
gtag/gtag.py
gtag/gtags.py
gtag-0.0.43.dist-info/LICENSE
gtag-0.0.43.dist-info/WHEEL
gtag-0.0.43.dist-info/METADATA
gtag-0.0.43.dist-info/RECORD
